mapof_elections-0.1.8.dist-info/RECORD
mapof_elections-0.1.8.dist-info/WHEEL
mapof_elections-0.1.8.dist-info/top_level.txt
mapof_elections-0.1.8.dist-info/METADATA
mapof_elections-0.1.8.dist-info/licenses/LICENSE.txt
mapof/elections/__init__.py
mapof/elections/cultures/params.py
mapof/elections/cultures/register.py
mapof/elections/cultures/pseudo_cultures.py
mapof/elections/cultures/__init__.py
mapof/elections/cultures/compass.py
mapof/elections/cultures/prefsampling_mask.py
mapof/elections/cultures/mallows.py
mapof/elections/cultures/alliances.py
mapof/elections/cultures/mallows_positionmatrices/29_matrix.txt
mapof/elections/cultures/mallows_positionmatrices/24_matrix.txt
mapof/elections/cultures/mallows_positionmatrices/13_matrix.txt
mapof/elections/cultures/mallows_positionmatrices/16_matrix.txt
mapof/elections/cultures/mallows_positionmatrices/21_matrix.txt
mapof/elections/cultures/mallows_positionmatrices/5_matrix.txt
mapof/elections/cultures/mallows_positionmatrices/30_matrix.txt
mapof/elections/cultures/mallows_positionmatrices/8_matrix.txt
mapof/elections/cultures/mallows_positionmatrices/2_matrix.txt
mapof/elections/cultures/mallows_positionmatrices/11_matrix.txt
mapof/elections/cultures/mallows_positionmatrices/26_matrix.txt
mapof/elections/cultures/mallows_positionmatrices/7_matrix.txt
mapof/elections/cultures/mallows_positionmatrices/23_matrix.txt
mapof/elections/cultures/mallows_positionmatrices/14_matrix.txt
mapof/elections/cultures/mallows_positionmatrices/19_matrix.txt
mapof/elections/cultures/mallows_positionmatrices/17_matrix.txt
mapof/elections/cultures/mallows_positionmatrices/20_matrix.txt
mapof/elections/cultures/mallows_positionmatrices/4_matrix.txt
mapof/elections/cultures/mallows_positionmatrices/9_matrix.txt
mapof/elections/cultures/mallows_positionmatrices/28_matrix.txt
mapof/elections/cultures/mallows_positionmatrices/25_matrix.txt
mapof/elections/cultures/mallows_positionmatrices/12_matrix.txt
mapof/elections/cultures/mallows_positionmatrices/6_matrix.txt
mapof/elections/cultures/mallows_positionmatrices/22_matrix.txt
mapof/elections/cultures/mallows_positionmatrices/15_matrix.txt
