Metadata-Version: 2.4
Name: mapof-elections
Version: 0.1.8
Summary: Map of Elections
Author-email: Stanislaw Szufa <s.szufa@gmail.com>, Niclas Boehmer <niclas.boehmer@tu-berlin.de>, Piotr Faliszewski <faliszew@agh.edu.pl>, Lukasz Janeczko <lukij1997@gmail.com>, Andrzej Kaczmarczyk <andrzej.kaczmarczyk@agh.edu.pl>, Tomasz Was <tomasz.t.was@gmail.com>
License: Copyright (c) 2018-2024 Stanislaw Szufa, Andrzej Kaczmarczyk, and others.
Classifier: Programming Language :: Python :: 3
Classifier: License :: OSI Approved :: MIT License
Classifier: Operating System :: OS Independent
Requires-Python: >=3.10
License-File: LICENSE.txt
Requires-Dist: mapof>=0.1.4
Requires-Dist: prefsampling~=0.1.24
Requires-Dist: tqdm==4.66.5
Requires-Dist: abcvoting~=2.11.0
Requires-Dist: matplotlib~=3.9.0
Requires-Dist: numpy>=2.0.0
Requires-Dist: gurobipy~=11.0.3
Requires-Dist: networkx~=3.1
Requires-Dist: pulp~=2.9.0
Requires-Dist: permanentbis~=0.1
Dynamic: license-file
